FITSxtractor/ExtractorClass.py
FITSxtractor/FITSClass.py
FITSxtractor/__init__.py
FITSxtractor/cli.py
FITSxtractor-0.9.2.dist-info/LICENSE
FITSxtractor-0.9.2.dist-info/METADATA
FITSxtractor-0.9.2.dist-info/WHEEL
FITSxtractor-0.9.2.dist-info/entry_points.txt
FITSxtractor-0.9.2.dist-info/top_level.txt
FITSxtractor-0.9.2.dist-info/RECORD
